{"metadata": {"dbt_schema_version": "https://schemas.getdbt.com/dbt/run-results/v4.json", "dbt_version": "1.5.2", "generated_at": "2024-08-10T09:44:58.549299Z", "invocation_id": "51db8bcf-d2a7-48c9-a7cc-5f0a1272ef59", "env": {}}, "results": [{"status": "success", "timing": [{"name": "compile", "started_at": "2024-08-10T09:44:56.713267Z", "completed_at": "2024-08-10T09:44:56.714747Z"}, {"name": "execute", "started_at": "2024-08-10T09:44:56.715543Z", "completed_at": "2024-08-10T09:44:56.715553Z"}], "thread_id": "Thread-1 (worker)", "execution_time": 0.003852367401123047, "adapter_response": {}, "message": null, "failures": null, "unique_id": "seed.dbtlearn.seed_full_moon_dates"}, {"status": "success", "timing": [{"name": "compile", "started_at": "2024-08-10T09:44:56.718129Z", "completed_at": "2024-08-10T09:44:56.721854Z"}, {"name": "execute", "started_at": "2024-08-10T09:44:56.722689Z", "completed_at": "2024-08-10T09:44:56.722700Z"}], "thread_id": "Thread-1 (worker)", "execution_time": 0.0061855316162109375, "adapter_response": {}, "message": null, "failures": null, "unique_id": "snapshot.dbtlearn.scd_raw_hosts"}, {"status": "success", "timing": [{"name": "compile", "started_at": "2024-08-10T09:44:56.725241Z", "completed_at": "2024-08-10T09:44:56.727994Z"}, {"name": "execute", "started_at": "2024-08-10T09:44:56.728802Z", "completed_at": "2024-08-10T09:44:56.728813Z"}], "thread_id": "Thread-1 (worker)", "execution_time": 0.005159854888916016, "adapter_response": {}, "message": null, "failures": null, "unique_id": "snapshot.dbtlearn.scd_raw_listings"}, {"status": "success", "timing": [{"name": "compile", "started_at": "2024-08-10T09:44:56.731393Z", "completed_at": "2024-08-10T09:44:56.736024Z"}, {"name": "execute", "started_at": "2024-08-10T09:44:56.736880Z", "completed_at": "2024-08-10T09:44:56.736889Z"}], "thread_id": "Thread-1 (worker)", "execution_time": 0.0075130462646484375, "adapter_response": {}, "message": null, "failures": null, "unique_id": "model.dbtlearn.dim_hosts_cleansed"}, {"status": "success", "timing": [{"name": "compile", "started_at": "2024-08-10T09:44:56.740549Z", "completed_at": "2024-08-10T09:44:56.745982Z"}, {"name": "execute", "started_at": "2024-08-10T09:44:56.746871Z", "completed_at": "2024-08-10T09:44:56.746879Z"}], "thread_id": "Thread-1 (worker)", "execution_time": 0.008439779281616211, "adapter_response": {}, "message": null, "failures": null, "unique_id": "model.dbtlearn.dim_listings_cleansed"}, {"status": "success", "timing": [{"name": "compile", "started_at": "2024-08-10T09:44:56.749792Z", "completed_at": "2024-08-10T09:44:56.774319Z"}, {"name": "execute", "started_at": "2024-08-10T09:44:56.775165Z", "completed_at": "2024-08-10T09:44:56.775173Z"}], "thread_id": "Thread-1 (worker)", "execution_time": 0.0270693302154541, "adapter_response": {}, "message": null, "failures": null, "unique_id": "model.dbtlearn.fct_review"}, {"status": "success", "timing": [{"name": "compile", "started_at": "2024-08-10T09:44:56.777933Z", "completed_at": "2024-08-10T09:44:56.789880Z"}, {"name": "execute", "started_at": "2024-08-10T09:44:56.790820Z", "completed_at": "2024-08-10T09:44:56.790828Z"}], "thread_id": "Thread-1 (worker)", "execution_time": 0.01448678970336914, "adapter_response": {}, "message": null, "failures": null, "unique_id": "test.dbtlearn.accepted_values_dim_hosts_cleansed_is_superhost__t__f.d6051554e4"}, {"status": "success", "timing": [{"name": "compile", "started_at": "2024-08-10T09:44:56.793417Z", "completed_at": "2024-08-10T09:44:56.853967Z"}, {"name": "execute", "started_at": "2024-08-10T09:44:56.854956Z", "completed_at": "2024-08-10T09:44:56.854966Z"}], "thread_id": "Thread-1 (worker)", "execution_time": 0.06321501731872559, "adapter_response": {}, "message": null, "failures": null, "unique_id": "test.dbtlearn.not_null_dim_hosts_cleansed_host_id.de84c3da05"}, {"status": "success", "timing": [{"name": "compile", "started_at": "2024-08-10T09:44:56.857624Z", "completed_at": "2024-08-10T09:44:56.861599Z"}, {"name": "execute", "started_at": "2024-08-10T09:44:56.862719Z", "completed_at": "2024-08-10T09:44:56.862726Z"}], "thread_id": "Thread-1 (worker)", "execution_time": 0.006797075271606445, "adapter_response": {}, "message": null, "failures": null, "unique_id": "test.dbtlearn.not_null_dim_hosts_cleansed_host_name.42386c5830"}, {"status": "success", "timing": [{"name": "compile", "started_at": "2024-08-10T09:44:56.865376Z", "completed_at": "2024-08-10T09:44:56.871374Z"}, {"name": "execute", "started_at": "2024-08-10T09:44:56.872276Z", "completed_at": "2024-08-10T09:44:56.872283Z"}], "thread_id": "Thread-1 (worker)", "execution_time": 0.008516788482666016, "adapter_response": {}, "message": null, "failures": null, "unique_id": "test.dbtlearn.unique_dim_hosts_cleansed_host_id.d7e4771347"}, {"status": "success", "timing": [{"name": "compile", "started_at": "2024-08-10T09:44:56.874894Z", "completed_at": "2024-08-10T09:44:56.877902Z"}, {"name": "execute", "started_at": "2024-08-10T09:44:56.878797Z", "completed_at": "2024-08-10T09:44:56.878804Z"}], "thread_id": "Thread-1 (worker)", "execution_time": 0.005540132522583008, "adapter_response": {}, "message": null, "failures": null, "unique_id": "model.dbtlearn.dim_listings_w_hosts"}, {"status": "success", "timing": [{"name": "compile", "started_at": "2024-08-10T09:44:56.881350Z", "completed_at": "2024-08-10T09:44:56.887142Z"}, {"name": "execute", "started_at": "2024-08-10T09:44:56.888079Z", "completed_at": "2024-08-10T09:44:56.888087Z"}], "thread_id": "Thread-1 (worker)", "execution_time": 0.008340120315551758, "adapter_response": {}, "message": null, "failures": null, "unique_id": "test.dbtlearn.accepted_values_dim_listings_cleansed_room_type__Entire_home_apt__Private_room__Shared_room__Hotel_room.a95127e3af"}, {"status": "success", "timing": [{"name": "compile", "started_at": "2024-08-10T09:44:56.890694Z", "completed_at": "2024-08-10T09:44:56.893592Z"}, {"name": "execute", "started_at": "2024-08-10T09:44:56.894572Z", "completed_at": "2024-08-10T09:44:56.894579Z"}], "thread_id": "Thread-1 (worker)", "execution_time": 0.005528926849365234, "adapter_response": {}, "message": null, "failures": null, "unique_id": "test.dbtlearn.dim_listings_minumum_nights"}, {"status": "success", "timing": [{"name": "compile", "started_at": "2024-08-10T09:44:56.897116Z", "completed_at": "2024-08-10T09:44:57.990329Z"}, {"name": "execute", "started_at": "2024-08-10T09:44:57.991189Z", "completed_at": "2024-08-10T09:44:57.991201Z"}], "thread_id": "Thread-1 (worker)", "execution_time": 1.5947835445404053, "adapter_response": {}, "message": null, "failures": null, "unique_id": "test.dbtlearn.no_nulls_in_dim_listings"}, {"status": "success", "timing": [{"name": "compile", "started_at": "2024-08-10T09:44:58.493224Z", "completed_at": "2024-08-10T09:44:58.497691Z"}, {"name": "execute", "started_at": "2024-08-10T09:44:58.498598Z", "completed_at": "2024-08-10T09:44:58.498606Z"}], "thread_id": "Thread-1 (worker)", "execution_time": 0.007081031799316406, "adapter_response": {}, "message": null, "failures": null, "unique_id": "test.dbtlearn.not_null_dim_listings_cleansed_host_id.084e4105be"}, {"status": "success", "timing": [{"name": "compile", "started_at": "2024-08-10T09:44:58.501165Z", "completed_at": "2024-08-10T09:44:58.505073Z"}, {"name": "execute", "started_at": "2024-08-10T09:44:58.505949Z", "completed_at": "2024-08-10T09:44:58.505956Z"}], "thread_id": "Thread-1 (worker)", "execution_time": 0.006449699401855469, "adapter_response": {}, "message": null, "failures": null, "unique_id": "test.dbtlearn.not_null_dim_listings_cleansed_listing_id.2da437bec9"}, {"status": "success", "timing": [{"name": "compile", "started_at": "2024-08-10T09:44:58.508557Z", "completed_at": "2024-08-10T09:44:58.513047Z"}, {"name": "execute", "started_at": "2024-08-10T09:44:58.513934Z", "completed_at": "2024-08-10T09:44:58.513941Z"}], "thread_id": "Thread-1 (worker)", "execution_time": 0.0070536136627197266, "adapter_response": {}, "message": null, "failures": null, "unique_id": "test.dbtlearn.positive_value_dim_listings_cleansed_minimum_nights.78fa6fc313"}, {"status": "success", "timing": [{"name": "compile", "started_at": "2024-08-10T09:44:58.516567Z", "completed_at": "2024-08-10T09:44:58.524163Z"}, {"name": "execute", "started_at": "2024-08-10T09:44:58.525079Z", "completed_at": "2024-08-10T09:44:58.525085Z"}], "thread_id": "Thread-1 (worker)", "execution_time": 0.010142087936401367, "adapter_response": {}, "message": null, "failures": null, "unique_id": "test.dbtlearn.relationships_dim_listings_cleansed_host_id__host_id__ref_dim_hosts_cleansed_.b53b94b2ad"}, {"status": "success", "timing": [{"name": "compile", "started_at": "2024-08-10T09:44:58.527741Z", "completed_at": "2024-08-10T09:44:58.531599Z"}, {"name": "execute", "started_at": "2024-08-10T09:44:58.532470Z", "completed_at": "2024-08-10T09:44:58.532477Z"}], "thread_id": "Thread-1 (worker)", "execution_time": 0.006358623504638672, "adapter_response": {}, "message": null, "failures": null, "unique_id": "test.dbtlearn.unique_dim_listings_cleansed_listing_id.930e4e859e"}, {"status": "success", "timing": [{"name": "compile", "started_at": "2024-08-10T09:44:58.535061Z", "completed_at": "2024-08-10T09:44:58.539511Z"}, {"name": "execute", "started_at": "2024-08-10T09:44:58.540352Z", "completed_at": "2024-08-10T09:44:58.540359Z"}], "thread_id": "Thread-1 (worker)", "execution_time": 0.006889820098876953, "adapter_response": {}, "message": null, "failures": null, "unique_id": "model.dbtlearn.full_moon_review"}, {"status": "success", "timing": [{"name": "compile", "started_at": "2024-08-10T09:44:58.542981Z", "completed_at": "2024-08-10T09:44:58.545855Z"}, {"name": "execute", "started_at": "2024-08-10T09:44:58.546728Z", "completed_at": "2024-08-10T09:44:58.546735Z"}], "thread_id": "Thread-1 (worker)", "execution_time": 0.005442619323730469, "adapter_response": {}, "message": null, "failures": null, "unique_id": "test.dbtlearn.consistent_created_at"}], "elapsed_time": 3.781620502471924, "args": {"log_format": "default", "favor_state": false, "populate_cache": true, "print": true, "project_dir": "/workspaces/dbt-bootcamp-codespace/dbtlearn", "static_parser": true, "compile": true, "which": "generate", "partial_parse": true, "indirect_selection": "eager", "enable_legacy_logger": false, "cache_selected_only": false, "exclude": [], "log_level": "info", "warn_error_options": {"include": [], "exclude": []}, "log_format_file": "debug", "use_colors_file": true, "write_json": true, "introspect": true, "macro_debugging": false, "quiet": false, "select": [], "printer_width": 80, "profiles_dir": "/home/vscode/.dbt", "version_check": true, "use_colors": true, "strict_mode": false, "log_level_file": "debug", "vars": {}, "send_anonymous_usage_stats": true, "log_path": "/workspaces/dbt-bootcamp-codespace/dbtlearn/logs", "defer": false}}